jira_tracker/__init__.py
jira_tracker/jira_auth.py
jira_tracker/logger.py
jira_tracker/project_tracker.py
jira_tracker/tracker_issue.py
jira_tracker-0.1.1.dist-info/LICENSE
jira_tracker-0.1.1.dist-info/METADATA
jira_tracker-0.1.1.dist-info/WHEEL
jira_tracker-0.1.1.dist-info/entry_points.txt
jira_tracker-0.1.1.dist-info/top_level.txt
jira_tracker-0.1.1.dist-info/RECORD
